inocloudreve/__init__.py
inocloudreve/client.py
inocloudreve/callback/__init__.py
inocloudreve/callback/complete_s3_upload.py
inocloudreve/file/__init__.py
inocloudreve/file/create_download_url.py
inocloudreve/file/create_download_url_utils.py
inocloudreve/file/delete_file.py
inocloudreve/file/force_unlock.py
inocloudreve/file/get_file_info.py
inocloudreve/file/list_files.py
inocloudreve/file/list_files_util.py
inocloudreve/file/update_file_content.py
inocloudreve/session/__init__.py
inocloudreve/session/generate_token.py
inocloudreve/session/generate_token_util.py
inocloudreve/session/password_sign_in.py
inocloudreve/session/refresh_token.py
inocloudreve/site/__init__.py
inocloudreve/site/ping.py
inocloudreve/upload/__init__.py
inocloudreve/upload/create_upload_session.py
inocloudreve/upload/delete_upload_session.py
inocloudreve/utils/__init__.py
inocloudreve/utils/download.py
inocloudreve/utils/files_utils.py
inocloudreve/utils/http.py
inocloudreve/utils/token_utils.py
inocloudreve/utils/upload.py
inocloudreve/workflow/__init__.py
inocloudreve/workflow/extract_archive.py
inocloudreve-0.2.6.dist-info/licenses/LICENSE
inocloudreve-0.2.6.dist-info/METADATA
inocloudreve-0.2.6.dist-info/WHEEL
inocloudreve-0.2.6.dist-info/top_level.txt
inocloudreve-0.2.6.dist-info/RECORD
