Metadata-Version: 2.4
Name: inocloudreve
Version: 0.2.6
Summary: Cloudreve api client
Author-email: Inoland <contact@inoland.net>
License-Expression: MPL-2.0
Project-URL: Homepage, https://github.com/nobandegani/InoCloudreve
Project-URL: Issues, https://github.com/nobandegani/InoCloudreve/issues
Classifier: Development Status :: 4 - Beta
Classifier: Intended Audience :: Developers
Classifier: Programming Language :: Python :: 3
Classifier: Operating System :: OS Independent
Requires-Python: >=3.9
License-File: LICENSE
Requires-Dist: httpx
Requires-Dist: httpx[http2]
Requires-Dist: aiofiles
Dynamic: license-file
